Workbook

Sheet Summary
A1: I-SEM wind, price and battery arbitrage - summary
A2: Trading days 1 Oct 2024 - 30 Sep 2026; test year = Oct 2025 - Sep 2026. Source data: Ember/SEMOpx, Energy-Charts/ENTSO-E, Open-Meteo. See Notes.
A4: KPI | B4: Value | C4: Unit | D4: Comment
A5: Mean DAM price (study period) | B5: =Monthly!B29 | C5: EUR/MWh | D5: Average of monthly means
A6: Highest monthly mean | B6: =Monthly!B31 | C6: EUR/MWh | D6: Sep 2026 - the level tracks GB/gas
A7: Hours at or below 5 EUR/MWh | B7: =Monthly!F29 | C7: hours | D7: 1.5% of hours; mostly night and midday
A8: Median daily spread (max - min) | B8: 104 | C8: EUR/MWh | D8: The battery revenue pool
A9: Merit-order effect | B9: 14.728 | C9: EUR/MWh per 10 pp | D9: Price fall per +10 points of wind penetration, within month
A10: Forecast MAE - LightGBM | B10: =Forecast!B8 | C10: EUR/MWh | D10: Test year
A11: Forecast MAE - naive (yesterday) | B11: =Forecast!B6 | C11: EUR/MWh | D11: Baseline
A12: Forecast improvement vs naive | B12: =Forecast!E8 | C12: % | D12: Lower MAE is better
A13: Battery revenue - perfect foresight | B13: =Battery!B18 | C13: EUR/MW/yr | D13: Upper bound
A14: Battery revenue - forecast-based | B14: =Battery!C18 | C14: EUR/MW/yr | D14: Optimised on LightGBM
A15: Battery revenue - simple rule | B15: =Battery!E18 | C15: EUR/MW/yr | D15: Fixed seasonal hours
A16: Share of perfect foresight captured | B16: =Battery!C18/Battery!B18 | C16: % | D16: Forecast strategy
A17: Value of forecasting | B17: =Battery!C18-Battery!E18 | C17: EUR/MW/yr | D17: Forecast minus rule

Sheet Monthly
A1: I-SEM day-ahead prices by trading month (EUR/MWh)
A2: Study period Oct 2024 - Sep 2026. Wind capture price = wind-weighted average price. Wind penetration = ROI wind / ROI load.
A4: Month | B4: Mean price | C4: Min | D4: Max | E4: Std dev | F4: Hours <= 5 EUR | G4: Negative hours | H4: Median daily spread | I4: Wind capture price | J4: Mean wind penetration | K4: Mean all-island wind (MW) | L4: GB mean price
A5: Oct 2024 | B5: 123.49609 | C5: 0 | D5: 315 | E5: 55.885209 | F5: 13 | G5: 0 | H5: 101.31 | I5: 105.6167 | J5: 0.35614138 | K5: 1642.2935 | L5: 100.59251
A6: Nov 2024 | B6: 148.75374 | C6: -4.12 | D6: 387.89 | E6: 61.105881 | F6: 14 | G6: 7 | H6: 140.12 | I6: 121.2536 | J6: 0.2935075 | K6: 1440.7743 | L6: 117.07157
A7: Dec 2024 | B7: 139.62215 | C7: 0 | D7: 499.99 | E7: 89.108242 | F7: 14 | G7: 0 | H7: 115.405 | I7: 108.104 | J7: 0.42782954 | K7: 2027.2928 | L7: 109.38617
A8: Jan 2025 | B8: 166.50821 | C8: 8 | D8: 494.1 | E8: 74.810335 | F8: 0 | G8: 0 | H8: 154.135 | I8: 142.20287 | J8: 0.34391562 | K8: 1710.2913 | L8: 141.1054
A9: Feb 2025 | B9: 141.1658 | C9: 21.42 | D9: 335 | E9: 47.861335 | F9: 0 | G9: 0 | H9: 83.96 | I9: 130.10827 | J9: 0.49974181 | K9: 2512.2564 | L9: 127.57354
A10: Mar 2025 | B10: 131.81841 | C10: 20.42 | D10: 366.21 | E10: 50.961802 | F10: 0 | G10: 0 | H10: 144.14 | I10: 115.89319 | J10: 0.33145081 | K10: 1621.7882 | L10: 106.42855
A11: Apr 2025 | B11: 111.00503 | C11: 0 | D11: 300 | E11: 39.740787 | F11: 3 | G11: 0 | H11: 109.335 | I11: 101.73891 | J11: 0.28383993 | K11: 1298.4817 | L11: 91.751306
A12: May 2025 | B12: 108.6653 | C12: -23.5 | D12: 237.39 | E12: 41.263244 | F12: 23 | G12: 16 | H12: 86.09 | I12: 89.76611 | J12: 0.22802731 | K12: 965.25347 | L12: 82.120309
A13: Jun 2025 | B13: 95.190736 | C13: -5.17 | D13: 224 | E13: 38.817507 | F13: 20 | G13: 4 | H13: 85.57 | I13: 84.093273 | J13: 0.30439162 | K13: 1328.6083 | L13: 79.027764
A14: Jul 2025 | B14: 99.652375 | C14: 10.87 | D14: 191.7 | E14: 22.71628 | F14: 0 | G14: 0 | H14: 54.235 | I14: 93.513182 | J14: 0.24677803 | K14: 1088.9307 | L14: 91.63168
A15: Aug 2025 | B15: 96.442567 | C15: 0 | D15: 288.98 | E15: 43.511145 | F15: 38 | G15: 0 | H15: 72.66 | I15: 77.581969 | J15: 0.27802869 | K15: 1184.9278 | L15: 82.602137
A16: Sep 2025 | B16: 94.284368 | C16: -3.19 | D16: 232.89 | E16: 46.905611 | F16: 29 | G16: 12 | H16: 114.32 | I16: 80.881815 | J16: 0.34483378 | K16: 1541.0337 | L16: 76.844944
... A28: Sep 2026 | B28: 182.74389 | C28: 0.38 | D28: 414.9 | E28: 65.513312 | F28: 13 | G28: 0 | H28: 149.41 | I28: 165.59708 | J28: 0.35311733 | K28: 1706.5796 | L28: 156.23668
A29: Average (hours: total) | B29: =AVERAGE(B5:B28) | C29: =AVERAGE(C5:C28) | D29: =AVERAGE(D5:D28) | E29: =AVERAGE(E5:E28) | F29: =SUM(F5:F28) | G29: =SUM(G5:G28) | H29: =AVERAGE(H5:H28) | I29: =AVERAGE(I5:I28) | J29: =AVERAGE(J5:J28) | K29: =AVERAGE(K5:K28) | L29: =AVERAGE(L5:L28)
A30: Minimum | B30: =MIN(B5:B28) | C30: =MIN(C5:C28) | D30: =MIN(D5:D28) | E30: =MIN(E5:E28) | F30: =MIN(F5:F28) | G30: =MIN(G5:G28) | H30: =MIN(H5:H28) | I30: =MIN(I5:I28) | ... L30: =MIN(L5:L28)
A31: Maximum | B31: =MAX(B5:B28) | C31: =MAX(C5:C28) | D31: =MAX(D5:D28) | E31: =MAX(E5:E28) | F31: =MAX(F5:F28) | G31: =MAX(G5:G28) | H31: =MAX(H5:H28) | I31: =MAX(I5:I28) | ... L31: =MAX(L5:L28)

Sheet Heatmap
A1: Average DAM price by hour (Irish local time) and trading month, EUR/MWh
A2: Conditional colour scale: blue = cheap, red = expensive.
A4: Hour | B4: Oct 24 | C4: Nov 24 | D4: Dec 24 | E4: Jan 25 | F4: Feb 25 | G4: Mar 25 | H4: Apr 25 | I4: May 25 | J4: Jun 25 | K4: Jul 25 | L4: Aug 25 | M4: Sep 25 | N4: Oct 25 | O4: Nov 25 | P4: Dec 25 | Q4: Jan 26 | R4: Feb 26 | S4: Mar 26 | T4: Apr 26 | U4: May 26 | V4: Jun 26 | W4: Jul 26 | X4: Aug 26 | Y4: Sep 26
A5: 00:00 | B5: 91.2 | C5: 109.5 | D5: 96 | E5: 122.9 | F5: 115.4 | G5: 111.2 | H5: 96.8 | I5: 103.2 | J5: 96.2 | K5: 96.1 | L5: 93 | M5: 68.3 | N5: 69.1 | O5: 86.4 | P5: 81.7 | Q5: 99.2 | R5: 94.3 | S5: 110.5 | T5: 129.4 | U5: 146.9 | V5: 137.4 | W5: 168.2 | X5: 171.2 | Y5: 175
A6: 01:00 | B6: 91.3 | C6: 107.2 | D6: 89.6 | E6: 121.1 | F6: 112.5 | G6: 110.9 | H6: 92 | I6: 95.3 | J6: 86.9 | K6: 91.3 | L6: 86.8 | M6: 65.1 | N6: 67.4 | O6: 80.4 | P6: 78.6 | Q6: 98 | R6: 92 | S6: 106.4 | T6: 122.1 | U6: 135.9 | V6: 127.8 | W6: 155 | X6: 159.1 | Y6: 166.1
A7: 02:00 | B7: 87.2 | C7: 104.6 | D7: 84.5 | E7: 116.6 | F7: 109.3 | G7: 105.4 | H7: 93 | I7: 97.5 | J7: 84.8 | K7: 89.1 | L7: 84.5 | M7: 64.7 | N7: 67.1 | O7: 78.8 | P7: 75.8 | Q7: 96.1 | R7: 91.9 | S7: 104.6 | T7: 125.2 | U7: 137.7 | V7: 129.4 | W7: 156.7 | X7: 158.2 | Y7: 165.4
A8: 03:00 | B8: 85 | C8: 101.8 | D8: 80.2 | E8: 114.6 | F8: 107.4 | G8: 102.8 | H8: 91.7 | I8: 94.6 | J8: 81.5 | K8: 87.4 | L8: 81.3 | M8: 64.3 | N8: 65.8 | O8: 75.4 | P8: 73.9 | Q8: 94.4 | R8: 87.9 | S8: 101.1 | T8: 120.6 | U8: 132.8 | V8: 125.4 | W8: 150.7 | X8: 153.1 | Y8: 161.6
A9: 04:00 | B9: 83.9 | C9: 100.4 | D9: 78.6 | E9: 111.3 | F9: 106.7 | G9: 100.9 | H9: 91.5 | I9: 93.7 | J9: 80 | K9: 87.1 | L9: 79.4 | M9: 65.1 | N9: 66 | O9: 74.3 | P9: 72.6 | Q9: 94 | R9: 85.2 | S9: 98.8 | T9: 117 | U9: 129.9 | V9: 122.5 | W9: 147.4 | X9: 154.1 | Y9: 161.6
A10: 05:00 | B10: 87.4 | C10: 101.6 | D10: 82.8 | E10: 111.2 | F10: 112.1 | G10: 106.7 | H10: 96.3 | I10: 94.3 | J10: 80.9 | K10: 87.7 | L10: 82.4 | M10: 70.7 | N10: 69.7 | O10: 75.8 | P10: 73.9 | Q10: 94.8 | R10: 83.8 | S10: 103 | T10: 116 | U10: 127.6 | V10: 119.9 | W10: 146.4 | X10: 161.9 | Y10: 170.6
A11: 06:00 | B11: 108 | C11: 114.8 | D11: 101.6 | E11: 126.9 | F11: 132.4 | G11: 126 | H11: 116 | I11: 107.8 | J11: 95.1 | K11: 99.6 | L11: 93.8 | M11: 91.7 | N11: 88.5 | O11: 91.7 | P11: 85.7 | Q11: 104.6 | R11: 92.4 | S11: 124.3 | T11: 132.2 | U11: 134 | V11: 126.9 | W11: 152.8 | X11: 168.8 | Y11: 191.6
A12: 07:00 | B12: 132.3 | C12: 138 | D12: 139 | E12: 157.6 | F12: 154.7 | G12: 146.1 | H12: 135.1 | I12: 125.2 | J12: 104 | K12: 108.7 | L12: 103.2 | M12: 118.3 | N12: 116.1 | O12: 115.3 | P12: 105.7 | Q12: 120.7 | R12: 104.2 | S12: 151 | T12: 157 | U12: 158.6 | V12: 143.4 | W12: 176.2 | X12: 176.9 | Y12: 212.9
A13: 08:00 | B13: 152.8 | C13: 156.6 | D13: 155.3 | E13: 182.7 | F13: 160 | G13: 150.3 | H13: 143.3 | I13: 134.4 | J13: 108.6 | K13: 113 | L13: 109.7 | M13: 131.7 | N13: 131.4 | O13: 136 | P13: 116.9 | Q13: 136.8 | R13: 113.2 | S13: 159.1 | T13: 165.4 | U13: 166.8 | V13: 146.1 | W13: 181.5 | X13: 183.4 | Y13: 220.1
A14: 09:00 | B14: 152.4 | C14: 169.2 | D14: 163.3 | E14: 197.9 | F14: 158.3 | G14: 142.6 | H14: 128.6 | I14: 124.2 | J14: 102.2 | K14: 107.2 | L14: 101.7 | M14: 122.2 | N14: 136.1 | O14: 145.1 | P14: 122.8 | Q14: 143.3 | R14: 116.3 | S14: 151.3 | T14: 158.5 | U14: 158.2 | V14: 135.9 | W14: 169.3 | X14: 174.6 | Y14: 208
A15: 10:00 | B15: 143 | C15: 165.2 | D15: 161.4 | E15: 194.2 | F15: 145.5 | G15: 122.6 | H15: 107.4 | I15: 105.1 | J15: 88.7 | K15: 98.7 | L15: 92.8 | M15: 99.6 | N15: 123 | O15: 136.5 | P15: 123.9 | Q15: 142.4 | R15: 111.1 | S15: 128.7 | T15: 132.5 | U15: 141 | V15: 120.9 | W15: 142.8 | X15: 158 | Y15: 172.4
A16: 11:00 | B16: 127 | C16: 160.2 | D16: 158.9 | E16: 188.9 | F16: 134.2 | G16: 108.3 | H16: 90.8 | I16: 93 | J16: 79.9 | K16: 90.5 | L16: 82.4 | M16: 80.6 | N16: 105.1 | O16: 126.5 | P16: 120.8 | Q16: 138.6 | R16: 105.4 | S16: 110.6 | T16: 112.2 | U16: 133.8 | V16: 114.2 | W16: 127.9 | X16: 146.1 | Y16: 142.8
... A28: 23:00 | B28: 96.4 | C28: 115.1 | D28: 112 | E28: 125.6 | F28: 118.4 | G28: 123.1 | H28: 106 | I28: 116.9 | J28: 110.6 | K28: 106.5 | L28: 102.9 | M28: 77.5 | N28: 76.7 | O28: 96.7 | P28: 86 | Q28: 104.9 | R28: 98 | S28: 118.4 | T28: 145 | U28: 160.2 | V28: 156.1 | W28: 187.8 | X28: 186.8 | Y28: 188.7

Sheet Battery
A1: Battery DAM arbitrage revenue, 1 MW / 2 MWh, 88% RTE, test year (EUR per MW)
A2: Perfect foresight = upper bound. Forecast = optimised on the LightGBM forecast, settled at actual prices. Rule = fixed seasonal hours from Year 1. DAM only - excludes system services, capacity, intraday, balancing.
A4: Month | B4: Perfect foresight | C4: Forecast (LightGBM) | D4: Forecast (naive) | E4: Simple rule | F4: Forecast capture | G4: Value of forecasting
A5: Oct 2025 | B5: 5274.31 | C5: 4261.35 | D5: 3088.72 | E5: 3324.21 | F5: =C5/B5 | G5: =C5-E5
A6: Nov 2025 | B6: 5976.96 | C6: 5428.91 | D6: 4606.43 | E6: 5486.4 | F6: =C6/B6 | G6: =C6-E6
A7: Dec 2025 | B7: 4197.46 | C7: 3339.95 | D7: 2720.38 | E7: 3565.19 | F7: =C7/B7 | G7: =C7-E7
A8: Jan 2026 | B8: 4288.43 | C8: 3631.16 | D8: 3474.31 | E8: 3604 | F8: =C8/B8 | G8: =C8-E8
A9: Feb 2026 | B9: 3014.64 | C9: 2508.66 | D9: 1831.08 | E9: 2187.08 | F9: =C9/B9 | G9: =C9-E9
A10: Mar 2026 | B10: 5351.37 | C10: 4258.64 | D10: 2650.33 | E10: 3251.56 | F10: =C10/B10 | G10: =C10-E10
A11: Apr 2026 | B11: 4932.71 | C11: 3176.02 | D11: 2675.67 | E11: 3252.04 | F11: =C11/B11 | G11: =C11-E11
A12: May 2026 | B12: 3207.41 | C12: 2524.69 | D12: 1583.99 | E12: 2110.84 | F12: =C12/B12 | G12: =C12-E12
A13: Jun 2026 | B13: 4565.27 | C13: 3694.4 | D13: 2757.36 | E13: 3635.5 | F13: =C13/B13 | G13: =C13-E13
A14: Jul 2026 | B14: 4211.48 | C14: 3114.81 | D14: 2738.17 | E14: 3200.14 | F14: =C14/B14 | G14: =C14-E14
A15: Aug 2026 | B15: 3961.03 | C15: 3203.04 | D15: 2836.7 | E15: 3423.88 | F15: =C15/B15 | G15: =C15-E15
A16: Sep 2026 | B16: 6656.77 | C16: 5254.7 | D16: 2463.93 | E16: 1960.18 | F16: =C16/B16 | G16: =C16-E16
A17: Total (scored days) | B17: =SUM(B5:B16) | C17: =SUM(C5:C16) | D17: =SUM(D5:D16) | E17: =SUM(E5:E16) | F17: =C17/B17 | G17: =C17-E17
A18: Annualised (x 365 / 359 days) | B18: =B17*365/359 | C18: =C17*365/359 | D18: =D17*365/359 | E18: =E17*365/359
A39: Sensitivity: forecast strategy, EUR per MW per year
A40: Duration | B40: 80% RTE | C40: 88% RTE | D40: 92% RTE
A41: 1 h (1 MWh) | B41: 18680.1 | C41: 23113.5 | D41: 25185.6
A42: 2 h (2 MWh) | B42: 36298.4 | C42: 45138.3 | D42: 49262.7
A43: 4 h (4 MWh) | B43: 66419 | C43: 83617.2 | D43: 91578.4

Sheet Forecast
A1: Day-ahead price forecast accuracy, test year (EUR/MWh)
A2: Information set = what is known at the D-1 11:00 gate closure. 'Upper bound' uses actual wind and is not a forecast.
A4: Model | B4: MAE | C4: RMSE | D4: Bias (mean error) | E4: MAE vs naive
A5: Naive: same hour last week | B5: 43.956306 | C5: 62.40791 | D5: -1.3793322 | E5: =1-B5/$B$6
A6: Naive: same hour yesterday | B6: 37.619501 | C6: 55.09061 | D6: -0.1162867 | E6: =1-B6/$B$6
A7: Linear regression | B7: 29.067087 | C7: 38.100598 | D7: -7.7847902 | E7: =1-B7/$B$6
A8: LightGBM | B8: 25.445015 | C8: 35.281819 | D8: -8.0192439 | E8: =1-B8/$B$6
A9: LightGBM (ICON weather) | B9: 25.718347 | C9: 35.74943 | D9: -8.4047679 | E9: =1-B9/$B$6
A10: Upper bound: + actual wind | B10: 24.794816 | C10: 34.508681 | D10: -7.9201539 | E10: =1-B10/$B$6
A13: MAE by delivery hour
A14: Hour | B14: Naive (yesterday) | C14: Linear | D14: LightGBM
A15: 00:00 | B15: 28.83 | C15: 29.49 | D15: 20.94
A16: 01:00 | B16: 26.07 | C16: 28.13 | D16: 19.47
A17: 02:00 | B17: 29.2 | C17: 29.39 | D17: 20.99
A18: 03:00 | B18: 28.64 | C18: 29.12 | D18: 20.48
A19: 04:00 | B19: 26.97 | C19: 28.59 | D19: 20.13
A20: 05:00 | B20: 25.14 | C20: 28.12 | D20: 20.17
A21: 06:00 | B21: 28.14 | C21: 28 | D21: 22.53
A22: 07:00 | B22: 42.85 | C22: 32.26 | D22: 29.61
A23: 08:00 | B23: 52.07 | C23: 35.4 | D23: 32.31
A24: 09:00 | B24: 56.58 | C24: 36.43 | D24: 33.38
A25: 10:00 | B25: 49.82 | C25: 31.03 | D25: 30.15
A26: 11:00 | B26: 43.53 | C26: 27.5 | D26: 27.16
... A38: 23:00 | B38: 34.58 | C38: 31.29 | D38: 23.45

Sheet Notes
A1: Sources, definitions and caveats
A3: - Prices: Ember European Wholesale Electricity Price Data (CC-BY-4.0, from SEMOpx), corrected -24 h; flat-price days replaced with official SEMOpx files or excluded (see docs/DECISIONS.md D9).
A4: - Wind and load: Energy-Charts (Fraunhofer ISE), ENTSO-E data; ROI = EirGrid area, NI = SONI area. Validated against EirGrid Smart Grid Dashboard (corr 0.998).
A5: - Weather forecasts: Open-Meteo Previous Runs API, ECMWF IFS 0.25, 48 h-ahead vintage, six locations (CC-BY-4.0).
A6: - Wind penetration uses ROI wind / ROI load because NI load is unpublished for 55% of the period (D8).
A7: - Trading day = 23:00-23:00 Irish local time. Hour columns are Irish local time.
A8: - Battery figures are DAM-only arbitrage: no system services, capacity, intraday or balancing revenue; no degradation, network charges or imbalance costs; price-taker assumption.
A9: - Every number is produced by code in src/ - see README for the one-command rebuild.
